zepben/ewb/__init__.py
zepben/ewb/exceptions.py
zepben/ewb/types.py
zepben/ewb/util.py
zepben/ewb/auth/__init__.py
zepben/ewb/auth/client/__init__.py
zepben/ewb/auth/client/zepben_token_fetcher.py
zepben/ewb/auth/common/__init__.py
zepben/ewb/auth/common/auth_exception.py
zepben/ewb/auth/common/auth_method.py
zepben/ewb/auth/common/auth_provider_config.py
zepben/ewb/database/__init__.py
zepben/ewb/database/paths/__init__.py
zepben/ewb/database/paths/database_type.py
zepben/ewb/database/paths/ewb_data_file_paths.py
zepben/ewb/database/paths/local_ewb_data_file_paths.py
zepben/ewb/database/sql/__init__.py
zepben/ewb/database/sql/column.py
zepben/ewb/database/sql/sql_table.py
zepben/ewb/database/sqlite/__init__.py
zepben/ewb/database/sqlite/common/__init__.py
zepben/ewb/database/sqlite/common/base_cim_reader.py
zepben/ewb/database/sqlite/common/base_cim_writer.py
zepben/ewb/database/sqlite/common/base_collection_reader.py
zepben/ewb/database/sqlite/common/base_collection_writer.py
zepben/ewb/database/sqlite/common/base_database_reader.py
zepben/ewb/database/sqlite/common/base_database_tables.py
zepben/ewb/database/sqlite/common/base_database_writer.py
zepben/ewb/database/sqlite/common/base_entry_writer.py
zepben/ewb/database/sqlite/common/base_service_reader.py
zepben/ewb/database/sqlite/common/base_service_writer.py
zepben/ewb/database/sqlite/common/metadata_collection_reader.py
zepben/ewb/database/sqlite/common/metadata_collection_writer.py
zepben/ewb/database/sqlite/common/metadata_entry_reader.py
zepben/ewb/database/sqlite/common/metadata_entry_writer.py
zepben/ewb/database/sqlite/common/reader_exceptions.py
zepben/ewb/database/sqlite/customer/__init__.py
zepben/ewb/database/sqlite/customer/customer_cim_reader.py
zepben/ewb/database/sqlite/customer/customer_cim_writer.py
zepben/ewb/database/sqlite/customer/customer_database_reader.py
zepben/ewb/database/sqlite/customer/customer_database_tables.py
zepben/ewb/database/sqlite/customer/customer_database_writer.py
zepben_ewb-1.1.0.dist-info/licenses/LICENSE
zepben_ewb-1.1.0.dist-info/METADATA
zepben_ewb-1.1.0.dist-info/WHEEL
zepben_ewb-1.1.0.dist-info/top_level.txt
zepben_ewb-1.1.0.dist-info/RECORD
