Metadata-Version: 2.4
Name: zepben.ewb
Version: 1.1.0
Summary: Python SDK for interacting with the Energy Workbench platform
Author-email: Kurt Greaves <kurt.greaves@zepben.com>, Max Chesterfield <max.chesterfield@zepben.com>
License-Expression: MPL-2.0
Project-URL: Repository, https://github.com/zepben/evolve-sdk-python
Project-URL: Homepage, https://zepben.com
Classifier: Programming Language :: Python :: 3
Classifier: Programming Language :: Python :: 3.10
Classifier: Programming Language :: Python :: 3.11
Classifier: Programming Language :: Python :: 3.12
Classifier: Operating System :: OS Independent
Requires-Python: <3.13,>=3.10
License-File: LICENSE
Requires-Dist: zepben.protobuf==1.0.0
Requires-Dist: typing_extensions==4.14.1
Requires-Dist: requests==2.32.5
Requires-Dist: urllib3==2.5.0
Requires-Dist: PyJWT==2.10.1
Requires-Dist: dataclassy==0.6.2
Provides-Extra: test
Requires-Dist: pytest==8.4.1; extra == "test"
Requires-Dist: pytest-cov==6.2.1; extra == "test"
Requires-Dist: pytest-asyncio==1.1.0; extra == "test"
Requires-Dist: pytest-timeout==2.4.0; extra == "test"
Requires-Dist: pytest-subtests==0.14.2; extra == "test"
Requires-Dist: hypothesis==6.140.3; extra == "test"
Requires-Dist: grpcio-testing==1.61.3; extra == "test"
Requires-Dist: pylint==2.14.5; extra == "test"
Requires-Dist: six==1.16.0; extra == "test"
Requires-Dist: tox; extra == "test"
Dynamic: license-file
